eigeningenuity/__init__.py
eigeningenuity/assetmodel.py
eigeningenuity/auth.py
eigeningenuity/commonmenu.py
eigeningenuity/elastic.py
eigeningenuity/events.py
eigeningenuity/historian.py
eigeningenuity/historianmulti.py
eigeningenuity/logformatter.py
eigeningenuity/settings.py
eigeningenuity/sql.py
eigeningenuity/util.py
eigeningenuity/core/__init__.py
local-tests/__init__.py
local-tests/common.py
local-tests/config.py
local-tests/demo.py
local-tests/run_tests.py
local-tests/historian/__init__.py
local-tests/historian/test_getCurrentDataPoints.py
local-tests/historian/test_getInterpolatedPoints.py
local-tests/historian/test_getInterpolatedRange.py
local-tests/historian/test_getMetaData.py
local-tests/historian/test_getRawDataPoints.py
local-tests/historian/test_listDataTags.py
local-tests/historian/test_writePoints.py
local-tests/historianmulti/__init__.py
local-tests/historianmulti/common_multi.py
local-tests/historianmulti/test_getClosestRawPoint.py
local-tests/historianmulti/test_getCurrentDataPoints.py
local-tests/historianmulti/test_getInterpolatedPoints.py
local-tests/historianmulti/test_getInterpolatedRange.py
local-tests/historianmulti/test_getMetaData.py
local-tests/historianmulti/test_getRawDatapoints.py
local-tests/historianmulti/test_listDataTags.py
local-tests/historianmulti/test_tagManagement.py
local-tests/historianmulti/test_writePoints.py
modelbuilder/__init__.py
modelbuilder/src/__init__.py
modelbuilder/src/assetmodelbuilder.py
modelbuilder/src/assetmodelcsvwriter.py
modelbuilder/src/assetmodelutilities.py
modelbuilder/src/configmanager.py
modelbuilder/src/csvcontentsmanager.py
modelbuilder/src/csvwriter.py
modelbuilder/src/fileanalyser.py
modelbuilder/src/filemanager.py
modelbuilder/src/messages.py
modelbuilder/src/property.py
modelbuilder/src/versionmanager.py
modelbuilder/src/connectors/__init__.py
modelbuilder/src/connectors/boltconnector.py
modelbuilder/src/connectors/dbconnectors.py
modelbuilder/src/connectors/genericconnector.py
python_eigen_ingenuity-0.5.23.dist-info/METADATA
python_eigen_ingenuity-0.5.23.dist-info/WHEEL
python_eigen_ingenuity-0.5.23.dist-info/entry_points.txt
python_eigen_ingenuity-0.5.23.dist-info/top_level.txt
python_eigen_ingenuity-0.5.23.dist-info/RECORD
