Metadata-Version: 2.4
Name: python-eigen-ingenuity
Version: 0.5.23
Summary: A python library used to query data from the Eigen Ingenuity system
Home-page: https://www.eigen.co/
Author: Murray Callander
Author-email: info@eigen.co
License: Apache License 2.0
Requires-Dist: numpy
Requires-Dist: pandas
Requires-Dist: pyserial
Requires-Dist: setuptools
Requires-Dist: urllib3
Requires-Dist: msal
Requires-Dist: cryptography
Requires-Dist: keyring
Requires-Dist: pyarrow
Requires-Dist: neo4j>=5.17.0
Requires-Dist: requests>=2.31.0
Requires-Dist: dateparser
Requires-Dist: importlib-metadata>=1.0; python_version < "3.8"
Dynamic: author
Dynamic: author-email
Dynamic: description
Dynamic: description-content-type
Dynamic: home-page
Dynamic: license
Dynamic: requires-dist
Dynamic: summary
